cloudtoken_plugin/__init__.py
cloudtoken_plugin/url_generator.py
cloudtoken_plugin.url_generator-0.1.764.dist-info/LICENSE.txt
cloudtoken_plugin.url_generator-0.1.764.dist-info/METADATA
cloudtoken_plugin.url_generator-0.1.764.dist-info/WHEEL
cloudtoken_plugin.url_generator-0.1.764.dist-info/top_level.txt
cloudtoken_plugin.url_generator-0.1.764.dist-info/RECORD
