Metadata-Version: 2.1
Name: cloudtoken-plugin.url-generator
Version: 0.1.764
Summary: URL generator plugin for cloudtoken.
Home-page: https://bitbucket.org/atlassian/cloudtoken
Author: David Ye
Author-email: dye@atlassian.com
License: Apache
Platform: UNKNOWN
Requires-Python: >=3.5
Requires-Dist: requests (>=2.20.1)
Requires-Dist: cloudtoken (>=0.1.12)
